{"created": 1775540291.4450006, "duration": 17.895139455795288, "exitcode": 0, "root": "C:\\Users\\rehan\\sqa-project", "environment": {}, "summary": {"passed": 23, "total": 23, "collected": 23}, "collectors": [{"nodeid": "", "outcome": "passed", "result": [{"nodeid": "tests", "type": "Dir"}]}, {"nodeid": "tests/test_basic.py", "outcome": "passed", "result": [{"nodeid": "tests/test_basic.py::test_get_user_success", "type": "Function", "lineno": 5}, {"nodeid": "tests/test_basic.py::test_get_all_posts", "type": "Function", "lineno": 18}, {"nodeid": "tests/test_basic.py::test_create_post", "type": "Function", "lineno": 31}, {"nodeid": "tests/test_basic.py::test_delete_post", "type": "Function", "lineno": 44}]}, {"nodeid": "tests/test_negative.py", "outcome": "passed", "result": [{"nodeid": "tests/test_negative.py::test_user_not_found", "type": "Function", "lineno": 5}, {"nodeid": "tests/test_negative.py::test_invalid_user_ids[0]", "type": "Function", "lineno": 15}, {"nodeid": "tests/test_negative.py::test_invalid_user_ids[-1]", "type": "Function", "lineno": 15}, {"nodeid": "tests/test_negative.py::test_invalid_user_ids[-999]", "type": "Function", "lineno": 15}, {"nodeid": "tests/test_negative.py::test_create_post_empty_title", "type": "Function", "lineno": 26}, {"nodeid": "tests/test_negative.py::test_create_post_empty_body", "type": "Function", "lineno": 36}]}, {"nodeid": "tests/test_performance.py", "outcome": "passed", "result": [{"nodeid": "tests/test_performance.py::test_single_user_response_time", "type": "Function", "lineno": 5}, {"nodeid": "tests/test_performance.py::test_all_posts_response_time", "type": "Function", "lineno": 20}]}, {"nodeid": "tests/test_schema.py", "outcome": "passed", "result": [{"nodeid": "tests/test_schema.py::test_user_required_fields", "type": "Function", "lineno": 4}, {"nodeid": "tests/test_schema.py::test_user_field_types", "type": "Function", "lineno": 16}, {"nodeid": "tests/test_schema.py::test_posts_list_structure", "type": "Function", "lineno": 31}]}, {"nodeid": "tests/test_users.py", "outcome": "passed", "result": [{"nodeid": "tests/test_users.py::test_multiple_users_exist[1]", "type": "Function", "lineno": 5}, {"nodeid": "tests/test_users.py::test_multiple_users_exist[2]", "type": "Function", "lineno": 5}, {"nodeid": "tests/test_users.py::test_multiple_users_exist[3]", "type": "Function", "lineno": 5}, {"nodeid": "tests/test_users.py::test_multiple_users_exist[4]", "type": "Function", "lineno": 5}, {"nodeid": "tests/test_users.py::test_multiple_users_exist[5]", "type": "Function", "lineno": 5}, {"nodeid": "tests/test_users.py::test_user_names_correct[1-Leanne Graham]", "type": "Function", "lineno": 18}, {"nodeid": "tests/test_users.py::test_user_names_correct[2-Ervin Howell]", "type": "Function", "lineno": 18}, {"nodeid": "tests/test_users.py::test_user_names_correct[3-Clementine Bauch]", "type": "Function", "lineno": 18}]}, {"nodeid": "tests", "outcome": "passed", "result": [{"nodeid": "tests/test_basic.py", "type": "Module"}, {"nodeid": "tests/test_negative.py", "type": "Module"}, {"nodeid": "tests/test_performance.py", "type": "Module"}, {"nodeid": "tests/test_schema.py", "type": "Module"}, {"nodeid": "tests/test_users.py", "type": "Module"}]}], "tests": [{"nodeid": "tests/test_basic.py::test_get_user_success", "lineno": 5, "outcome": "passed", "keywords": ["test_get_user_success", "smoke", "allure_label", "allure_description", "pytestmark", "__allure_display_name__", "test_basic.py", "tests", "sqa-project", ""], "setup": {"duration": 0.000296499998512445, "outcome": "passed"}, "call": {"duration": 0.6174602999999479, "outcome": "passed"}, "teardown": {"duration": 0.0002674000006663846, "outcome": "passed"}}, {"nodeid": "tests/test_basic.py::test_get_all_posts", "lineno": 18, "outcome": "passed", "keywords": ["test_get_all_posts", "smoke", "allure_label", "allure_description", "pytestmark", "__allure_display_name__", "test_basic.py", "tests", "sqa-project", ""], "setup": {"duration": 0.00015019999955256935, "outcome": "passed"}, "call": {"duration": 0.6580547000012302, "outcome": "passed"}, "teardown": {"duration": 0.0004882000012003118, "outcome": "passed"}}, {"nodeid": "tests/test_basic.py::test_create_post", "lineno": 31, "outcome": "passed", "keywords": ["test_create_post", "smoke", "allure_label", "allure_description", "pytestmark", "__allure_display_name__", "test_basic.py", "tests", "sqa-project", ""], "setup": {"duration": 0.0002325000004930189, "outcome": "passed"}, "call": {"duration": 0.903790399999707, "outcome": "passed"}, "teardown": {"duration": 0.0002537000000302214, "outcome": "passed"}}, {"nodeid": "tests/test_basic.py::test_delete_post", "lineno": 44, "outcome": "passed", "keywords": ["test_delete_post", "regression", "allure_label", "allure_description", "pytestmark", "__allure_display_name__", "test_basic.py", "tests", "sqa-project", ""], "setup": {"duration": 0.0002939000005426351, "outcome": "passed"}, "call": {"duration": 0.8291505000015604, "outcome": "passed"}, "teardown": {"duration": 0.0004116000000067288, "outcome": "passed"}}, {"nodeid": "tests/test_negative.py::test_user_not_found", "lineno": 5, "outcome": "passed", "keywords": ["test_user_not_found", "negative", "allure_label", "allure_description", "pytestmark", "__allure_display_name__", "test_negative.py", "tests", "sqa-project", ""], "setup": {"duration": 0.00043449999975564424, "outcome": "passed"}, "call": {"duration": 0.7142898000001878, "outcome": "passed"}, "teardown": {"duration": 0.0005826999986311421, "outcome": "passed"}}, {"nodeid": "tests/test_negative.py::test_invalid_user_ids[0]", "lineno": 15, "outcome": "passed", "keywords": ["test_invalid_user_ids[0]", "parametrize", "negative", "allure_label", "allure_description", "pytestmark", "__allure_display_name__", "0", "test_negative.py", "tests", "sqa-project", ""], "setup": {"duration": 0.00046160000056261197, "outcome": "passed"}, "call": {"duration": 0.7134459000008064, "outcome": "passed"}, "teardown": {"duration": 0.0003827999989880482, "outcome": "passed"}}, {"nodeid": "tests/test_negative.py::test_invalid_user_ids[-1]", "lineno": 15, "outcome": "passed", "keywords": ["test_invalid_user_ids[-1]", "parametrize", "negative", "allure_label", "allure_description", "pytestmark", "__allure_display_name__", "-1", "test_negative.py", "tests", "sqa-project", ""], "setup": {"duration": 0.0006210999999893829, "outcome": "passed"}, "call": {"duration": 0.8161022999993293, "outcome": "passed"}, "teardown": {"duration": 0.00029829999948560726, "outcome": "passed"}}, {"nodeid": "tests/test_negative.py::test_invalid_user_ids[-999]", "lineno": 15, "outcome": "passed", "keywords": ["test_invalid_user_ids[-999]", "parametrize", "negative", "allure_label", "allure_description", "pytestmark", "__allure_display_name__", "-999", "test_negative.py", "tests", "sqa-project", ""], "setup": {"duration": 0.0006548000001203036, "outcome": "passed"}, "call": {"duration": 0.7167191999997158, "outcome": "passed"}, "teardown": {"duration": 0.0005295000009937212, "outcome": "passed"}}, {"nodeid": "tests/test_negative.py::test_create_post_empty_title", "lineno": 26, "outcome": "passed", "keywords": ["test_create_post_empty_title", "negative", "allure_label", "allure_description", "pytestmark", "__allure_display_name__", "test_negative.py", "tests", "sqa-project", ""], "setup": {"duration": 0.00026059999981953297, "outcome": "passed"}, "call": {"duration": 1.4259219000014127, "outcome": "passed"}, "teardown": {"duration": 0.00033679999978630804, "outcome": "passed"}}, {"nodeid": "tests/test_negative.py::test_create_post_empty_body", "lineno": 36, "outcome": "passed", "keywords": ["test_create_post_empty_body", "negative", "allure_label", "allure_description", "pytestmark", "__allure_display_name__", "test_negative.py", "tests", "sqa-project", ""], "setup": {"duration": 0.000259300000834628, "outcome": "passed"}, "call": {"duration": 1.3289843000002293, "outcome": "passed"}, "teardown": {"duration": 0.00038099999983387534, "outcome": "passed"}}, {"nodeid": "tests/test_performance.py::test_single_user_response_time", "lineno": 5, "outcome": "passed", "keywords": ["test_single_user_response_time", "regression", "allure_label", "allure_description", "pytestmark", "__allure_display_name__", "test_performance.py", "tests", "sqa-project", ""], "setup": {"duration": 0.00021099999867146835, "outcome": "passed"}, "call": {"duration": 0.6089334999996936, "outcome": "passed", "stdout": "\nResponse time: 0.606s\n"}, "teardown": {"duration": 0.00033239999902434647, "outcome": "passed"}}, {"nodeid": "tests/test_performance.py::test_all_posts_response_time", "lineno": 20, "outcome": "passed", "keywords": ["test_all_posts_response_time", "regression", "allure_label", "allure_description", "pytestmark", "__allure_display_name__", "test_performance.py", "tests", "sqa-project", ""], "setup": {"duration": 0.0003361999988555908, "outcome": "passed"}, "call": {"duration": 0.6484393999999156, "outcome": "passed", "stdout": "\nResponse time: 0.646s\n"}, "teardown": {"duration": 0.0004468000006454531, "outcome": "passed"}}, {"nodeid": "tests/test_schema.py::test_user_required_fields", "lineno": 4, "outcome": "passed", "keywords": ["test_user_required_fields", "regression", "allure_label", "allure_description", "pytestmark", "__allure_display_name__", "test_schema.py", "tests", "sqa-project", ""], "setup": {"duration": 0.0005564000002777902, "outcome": "passed"}, "call": {"duration": 0.5570791999998619, "outcome": "passed"}, "teardown": {"duration": 0.0006171999993966892, "outcome": "passed"}}, {"nodeid": "tests/test_schema.py::test_user_field_types", "lineno": 16, "outcome": "passed", "keywords": ["test_user_field_types", "regression", "allure_label", "allure_description", "pytestmark", "__allure_display_name__", "test_schema.py", "tests", "sqa-project", ""], "setup": {"duration": 0.0008438000004389323, "outcome": "passed"}, "call": {"duration": 0.7119835999983479, "outcome": "passed"}, "teardown": {"duration": 0.0004702000005636364, "outcome": "passed"}}, {"nodeid": "tests/test_schema.py::test_posts_list_structure", "lineno": 31, "outcome": "passed", "keywords": ["test_posts_list_structure", "regression", "allure_label", "allure_description", "pytestmark", "__allure_display_name__", "test_schema.py", "tests", "sqa-project", ""], "setup": {"duration": 0.00039259999903151765, "outcome": "passed"}, "call": {"duration": 0.6487020000004122, "outcome": "passed"}, "teardown": {"duration": 0.000527600001078099, "outcome": "passed"}}, {"nodeid": "tests/test_users.py::test_multiple_users_exist[1]", "lineno": 5, "outcome": "passed", "keywords": ["test_multiple_users_exist[1]", "parametrize", "smoke", "allure_label", "allure_description", "pytestmark", "__allure_display_name__", "1", "test_users.py", "tests", "sqa-project", ""], "setup": {"duration": 0.0007774000005156267, "outcome": "passed"}, "call": {"duration": 0.6922864000007394, "outcome": "passed"}, "teardown": {"duration": 0.0005698000004485948, "outcome": "passed"}}, {"nodeid": "tests/test_users.py::test_multiple_users_exist[2]", "lineno": 5, "outcome": "passed", "keywords": ["test_multiple_users_exist[2]", "parametrize", "smoke", "allure_label", "allure_description", "pytestmark", "__allure_display_name__", "2", "test_users.py", "tests", "sqa-project", ""], "setup": {"duration": 0.000522300000739051, "outcome": "passed"}, "call": {"duration": 0.8151234999986627, "outcome": "passed"}, "teardown": {"duration": 0.00037089999932504725, "outcome": "passed"}}, {"nodeid": "tests/test_users.py::test_multiple_users_exist[3]", "lineno": 5, "outcome": "passed", "keywords": ["test_multiple_users_exist[3]", "parametrize", "smoke", "allure_label", "allure_description", "pytestmark", "__allure_display_name__", "3", "test_users.py", "tests", "sqa-project", ""], "setup": {"duration": 0.0007834999996703118, "outcome": "passed"}, "call": {"duration": 0.7120474999992439, "outcome": "passed"}, "teardown": {"duration": 0.0004470999992918223, "outcome": "passed"}}, {"nodeid": "tests/test_users.py::test_multiple_users_exist[4]", "lineno": 5, "outcome": "passed", "keywords": ["test_multiple_users_exist[4]", "parametrize", "smoke", "allure_label", "allure_description", "pytestmark", "__allure_display_name__", "4", "test_users.py", "tests", "sqa-project", ""], "setup": {"duration": 0.00043879999975615647, "outcome": "passed"}, "call": {"duration": 0.714343399999052, "outcome": "passed"}, "teardown": {"duration": 0.00026189999880443793, "outcome": "passed"}}, {"nodeid": "tests/test_users.py::test_multiple_users_exist[5]", "lineno": 5, "outcome": "passed", "keywords": ["test_multiple_users_exist[5]", "parametrize", "smoke", "allure_label", "allure_description", "pytestmark", "__allure_display_name__", "5", "test_users.py", "tests", "sqa-project", ""], "setup": {"duration": 0.0007203999994089827, "outcome": "passed"}, "call": {"duration": 0.6379085999997187, "outcome": "passed"}, "teardown": {"duration": 0.0005595000002358574, "outcome": "passed"}}, {"nodeid": "tests/test_users.py::test_user_names_correct[1-Leanne Graham]", "lineno": 18, "outcome": "passed", "keywords": ["test_user_names_correct[1-Leanne Graham]", "parametrize", "regression", "allure_label", "allure_description", "pytestmark", "__allure_display_name__", "1-Leanne Graham", "test_users.py", "tests", "sqa-project", ""], "setup": {"duration": 0.0006532999996125, "outcome": "passed"}, "call": {"duration": 0.6848417000001064, "outcome": "passed"}, "teardown": {"duration": 0.0003285000002506422, "outcome": "passed"}}, {"nodeid": "tests/test_users.py::test_user_names_correct[2-Ervin Howell]", "lineno": 18, "outcome": "passed", "keywords": ["test_user_names_correct[2-Ervin Howell]", "parametrize", "regression", "allure_label", "allure_description", "pytestmark", "__allure_display_name__", "2-Ervin Howell", "test_users.py", "tests", "sqa-project", ""], "setup": {"duration": 0.00036890000046696514, "outcome": "passed"}, "call": {"duration": 0.8128490999988571, "outcome": "passed"}, "teardown": {"duration": 0.00026980000075127464, "outcome": "passed"}}, {"nodeid": "tests/test_users.py::test_user_names_correct[3-Clementine Bauch]", "lineno": 18, "outcome": "passed", "keywords": ["test_user_names_correct[3-Clementine Bauch]", "parametrize", "regression", "allure_label", "allure_description", "pytestmark", "__allure_display_name__", "3-Clementine Bauch", "test_users.py", "tests", "sqa-project", ""], "setup": {"duration": 0.0006625000005442416, "outcome": "passed"}, "call": {"duration": 0.6452714999995806, "outcome": "passed"}, "teardown": {"duration": 0.00047820000145293307, "outcome": "passed"}}]}